feezfuzz-0.1.4.6.dist-info/METADATA
feezfuzz-0.1.4.6.dist-info/WHEEL
feezfuzz-0.1.4.6.dist-info/licenses/LICENSE
feezfuzz/__init__.py
feezfuzz/__main__.py
feezfuzz/build.py
feezfuzz/enums/__init__.py
feezfuzz/enums/cardtypes.py
feezfuzz/enums/columnnames.py
feezfuzz/enums/datatypes.py
feezfuzz/enums/instructions.py
feezfuzz/enums/slotnames.py
feezfuzz/enums/spellclasses.py
feezfuzz/enums/uuidgroups.py
feezfuzz/enums/uuidtypes.py
feezfuzz/io_utils.py
feezfuzz/nodes/byte.py
feezfuzz/nodes/cardid.py
feezfuzz/nodes/cell.py
feezfuzz/nodes/column.py
feezfuzz/nodes/command.py
feezfuzz/nodes/indextable.py
feezfuzz/nodes/level.py
feezfuzz/nodes/row.py
feezfuzz/nodes/script.py
feezfuzz/nodes/string.py
feezfuzz/nodes/table.py
feezfuzz/nodes/uint.py
feezfuzz/nodes/ushort.py
feezfuzz/nodes/uuid.py
feezfuzz-0.1.4.6.dist-info/RECORD
