Metadata-Version: 2.1
Name: feezfuzz
Version: 0.1.4.6
Summary: A WIP parser for Zanzarah's Data files.
Author-Email: AcipenserSturio <AcipenserSturio@users.noreply.github.com>
License: MIT
Requires-Python: >=3.10
Requires-Dist: tomli>=2.0.1
Requires-Dist: tomli-w>=1.0.0
